textparser.py
textparser-0.23.0.dist-info/LICENSE
textparser-0.23.0.dist-info/METADATA
textparser-0.23.0.dist-info/WHEEL
textparser-0.23.0.dist-info/top_level.txt
textparser-0.23.0.dist-info/RECORD
