Metadata-Version: 1.1
Name: textparser
Version: 0.23.0
Summary: Text parser.
Home-page: https://github.com/eerimoq/textparser
Author: Erik Moqvist
Author-email: erik.moqvist@gmail.com
License: MIT
Keywords: parser,parsing
Platform: UNKNOWN
Classifier: License :: OSI Approved :: MIT License
Classifier: Programming Language :: Python :: 2
Classifier: Programming Language :: Python :: 3
